explainable_transformers/__init__.py
explainable_transformers/image_explainer.py
explainable_transformers/text_explainer.py
explainable_transformers/utils.py
explainable_transformers-0.0.1.dist-info/LICENSE
explainable_transformers-0.0.1.dist-info/METADATA
explainable_transformers-0.0.1.dist-info/WHEEL
explainable_transformers-0.0.1.dist-info/top_level.txt
explainable_transformers-0.0.1.dist-info/RECORD
