Metadata-Version: 2.1
Name: explainable-transformers
Version: 0.0.1
Summary: Explanation techniques for Transformer-based architectures
Home-page: https://github.com/wilsonjr/explainable_transformer
Author: Wilson Estécio Marcílio Júnior
Author-email: wilson_jr@outlook.com
License: MIT
Platform: UNKNOWN
License-File: LICENSE
Requires-Dist: tqdm
Requires-Dist: numpy
Requires-Dist: opencv-python
Requires-Dist: torch
